grammarette/__init__.py
grammarette/_version.py
grammarette/grammarette.py
grammarette/msa.py
grammarette-0.0.0.dist-info/LICENSE.md
grammarette-0.0.0.dist-info/METADATA
grammarette-0.0.0.dist-info/WHEEL
grammarette-0.0.0.dist-info/top_level.txt
grammarette-0.0.0.dist-info/RECORD
