Metadata-Version: 2.1
Name: grammarette
Version: 0.0.0
Summary: A lightweight grammar inducer for toy lexicons
Home-page: https://github.com/jwcarr/grammarette
Author: Jon Carr
Author-email: jon.carr@rhul.ac.uk
License: GPLv3
Classifier: Programming Language :: Python :: 3
Classifier: License :: OSI Approved :: MIT License
Classifier: Operating System :: OS Independent
Classifier: Development Status :: 3 - Alpha
Classifier: Intended Audience :: Science/Research
Requires-Python: >=3.8
License-File: LICENSE.md
Requires-Dist: numpy (>=1.20)
Requires-Dist: scipy (>=1.5)
